__init__.py
check.py
bluefin_client_sui/__init__.py
bluefin_client_sui/account.py
bluefin_client_sui/api_service.py
bluefin_client_sui/client.py
bluefin_client_sui/constants.py
bluefin_client_sui/contracts.py
bluefin_client_sui/enumerations.py
bluefin_client_sui/interfaces.py
bluefin_client_sui/onboarding_signer.py
bluefin_client_sui/order_signer.py
bluefin_client_sui/rpc.py
bluefin_client_sui/signer.py
bluefin_client_sui/socket_manager.py
bluefin_client_sui/sockets_lib.py
bluefin_client_sui/utilities.py
bluefin_client_sui/websocket_client.py
bluefin_client_sui-2.0.0.dist-info/LICENSE
bluefin_client_sui-2.0.0.dist-info/METADATA
bluefin_client_sui-2.0.0.dist-info/WHEEL
bluefin_client_sui-2.0.0.dist-info/top_level.txt
bluefin_client_sui-2.0.0.dist-info/RECORD
