Metadata-Version: 2.1
Name: bluefin-client-sui
Version: 2.0.0
Summary: Library to interact with firefly exchange protocol including its off-chain api-gateway and on-chain contracts
Project-URL: Homepage, https://github.com/fireflyprotocol/bluefin-client-python-sui
Project-URL: Bug Reports, https://github.com/fireflyprotocol/bluefin-client-python-sui/issues
Project-URL: Source, https://github.com/fireflyprotocol/bluefin-client-python-sui
Keywords: bluefin,exchange,decentralized,perpetuals,blockchain
Requires-Python: >=3.8
License-File: LICENSE
Requires-Dist: web3 ~=5.31.3
Requires-Dist: requests ~=2.28.1
Requires-Dist: python-socketio ~=5.7.2
Requires-Dist: websocket-client ~=1.5.1
